async_sms_activate/__init__.py
async_sms_activate/activation.py
async_sms_activate/client.py
async_sms_activate/country.py
async_sms_activate/enums.py
async_sms_activate/errors.py
async_sms_activate/logger.py
async_sms_activate/py.typed
async_sms_activate-0.1.2.dist-info/LICENSE
async_sms_activate-0.1.2.dist-info/METADATA
async_sms_activate-0.1.2.dist-info/WHEEL
async_sms_activate-0.1.2.dist-info/top_level.txt
async_sms_activate-0.1.2.dist-info/RECORD
