Metadata-Version: 2.1
Name: async-sms-activate
Version: 0.1.2
Summary: Async API wrapper for sms-activate.org
Author-email: Rune Tech <runetech2024@gmail.com>
License: The MIT License (MIT)
Project-URL: Homepage, https://github.com/runetech0/sms-activate-api
Project-URL: github, https://github.com/runetech0/sms-activate-api
Keywords: sms-activate.org,async
Requires-Python: >=3.11
License-File: LICENSE
Requires-Dist: aiohttp >=3.10.10
Requires-Dist: aiohttp-socks >=0.9.0
